{
  "total": 456600500,
  "groupedByArea": [
    {
      "area": "ด้านบริหารทั่วไป",
      "total": 112467040,
      "plans": [
        {
          "plan": "บริหารงานทั่วไป",
          "total": 106406960
        },
        {
          "plan": "การรักษาความสงบภายใน",
          "total": 6060080
        }
      ]
    },
    {
      "area": "ด้านบริการชุมชนและสังคม",
      "total": 66731300,
      "plans": [
        {
          "plan": "การศึกษา",
          "total": 4694520
        },
        {
          "plan": "สาธารณสุข",
          "total": 15865600
        },
        {
          "plan": "สังคมสงเคราะห์",
          "total": 24863660
        },
        {
          "plan": "เคหะและชุมชน",
          "total": 700000
        },
        {
          "plan": "สร้างความเข้มแข็งของชุมชน",
          "total": 2837000
        },
        {
          "plan": "การศาสนา วัฒนธรรม และนันทนาการ",
          "total": 17770520
        }
      ]
    },
    {
      "area": "ด้านการเศรษฐกิจ",
      "total": 253476760,
      "plans": [
        {
          "plan": "อุตสาหกรรมและการโยธา",
          "total": 238710320
        },
        {
          "plan": "การเกษตร",
          "total": 11802040
        },
        {
          "plan": "การพาณิชย์",
          "total": 2964400
        }
      ]
    },
    {
      "area": "ด้านการดำเนินงานอื่น ๆ ",
      "total": 23925400,
      "plans": [
        {
          "plan": "งบกลาง",
          "total": 23925400
        }
      ]
    }
  ],
  "groupedByType": [
    {
      "type": "งบบุคลากร",
      "total": 128922320
    },
    {
      "type": "งบดำเนินงาน",
      "total": 126154280
    },
    {
      "type": "งบลงทุน",
      "total": 176898500
    },
    {
      "type": "งบเงินอุดหนุน",
      "total": 700000
    },
    {
      "type": "งบกลาง",
      "total": 23925400
    }
  ],
  "tasks": [
    {
      "task": "บริหารทั่วไป",
      "area": "ด้านบริหารทั่วไป",
      "plan": "บริหารงานทั่วไป",
      "type": "งบบุคลากร",
      "total": 39798700
    },
    {
      "task": "บริหารทั่วไป",
      "area": "ด้านบริหารทั่วไป",
      "plan": "บริหารงานทั่วไป",
      "type": "งบดำเนินงาน",
      "total": 31435400
    },
    {
      "task": "บริหารทั่วไป",
      "area": "ด้านบริหารทั่วไป",
      "plan": "บริหารงานทั่วไป",
      "type": "งบลงทุน",
      "total": 267500
    },
    {
      "task": "วางแผนสถิติและวิชาการ",
      "area": "ด้านบริหารทั่วไป",
      "plan": "บริหารงานทั่วไป",
      "type": "งบบุคลากร",
      "total": 7981320
    },
    {
      "task": "วางแผนสถิติและวิชาการ",
      "area": "ด้านบริหารทั่วไป",
      "plan": "บริหารงานทั่วไป",
      "type": "งบดำเนินงาน",
      "total": 3112000
    },
    {
      "task": "วางแผนสถิติและวิชาการ",
      "area": "ด้านบริหารทั่วไป",
      "plan": "บริหารงานทั่วไป",
      "type": "งบลงทุน",
      "total": 376800
    },
    {
      "task": "บริหารงานคลัง",
      "area": "ด้านบริหารทั่วไป",
      "plan": "บริหารงานทั่วไป",
      "type": "งบบุคลากร",
      "total": 14523600
    },
    {
      "task": "บริหารงานคลัง",
      "area": "ด้านบริหารทั่วไป",
      "plan": "บริหารงานทั่วไป",
      "type": "งบดำเนินงาน",
      "total": 6728400
    },
    {
      "task": "บริหารงานคลัง",
      "area": "ด้านบริหารทั่วไป",
      "plan": "บริหารงานทั่วไป",
      "type": "งบลงทุน",
      "total": 308700
    },
    {
      "task": "ควบคุมภายในและการตรวจสอบภายใน",
      "area": "ด้านบริหารทั่วไป",
      "plan": "บริหารงานทั่วไป",
      "type": "งบบุคลากร",
      "total": 1395540
    },
    {
      "task": "ควบคุมภายในและการตรวจสอบภายใน",
      "area": "ด้านบริหารทั่วไป",
      "plan": "บริหารงานทั่วไป",
      "type": "งบดำเนินงาน",
      "total": 474000
    },
    {
      "task": "ควบคุมภายในและการตรวจสอบภายใน",
      "area": "ด้านบริหารทั่วไป",
      "plan": "บริหารงานทั่วไป",
      "type": "งบลงทุน",
      "total": 5000
    },
    {
      "task": "บริหารทั่วไปเกี่ยวกับการรักษาความสงบภายใน",
      "area": "ด้านบริหารทั่วไป",
      "plan": "การรักษาความสงบภายใน",
      "type": "งบบุคลากร",
      "total": 2632680
    },
    {
      "task": "ป้องกันและบรรเทาสาธารณภัย",
      "area": "ด้านบริหารทั่วไป",
      "plan": "การรักษาความสงบภายใน",
      "type": "งบดำเนินงาน",
      "total": 2871400
    },
    {
      "task": "ป้องกันและบรรเทาสาธารณภัย",
      "area": "ด้านบริหารทั่วไป",
      "plan": "การรักษาความสงบภายใน",
      "type": "งบลงทุน",
      "total": 556000
    },
    {
      "task": "บริหารทั่วไปเกี่ยวกับการศึกษา",
      "area": "ด้านบริการชุมชนและสังคม",
      "plan": "การศึกษา",
      "type": "งบบุคลากร",
      "total": 2377920
    },
    {
      "task": "บริหารทั่วไปเกี่ยวกับการศึกษา",
      "area": "ด้านบริการชุมชนและสังคม",
      "plan": "การศึกษา",
      "type": "งบดำเนินงาน",
      "total": 1764600
    },
    {
      "task": "บริหารทั่วไปเกี่ยวกับการศึกษา",
      "area": "ด้านบริการชุมชนและสังคม",
      "plan": "การศึกษา",
      "type": "งบลงทุน",
      "total": 252000
    },
    {
      "task": "ระดับก่อนวัยเรียนและประถมศึกษา",
      "area": "ด้านบริการชุมชนและสังคม",
      "plan": "การศึกษา",
      "type": "งบดำเนินงาน",
      "total": 300000
    },
    {
      "task": "บริหารทั่วไปเกี่ยวกับสาธารณสุข",
      "area": "ด้านบริการชุมชนและสังคม",
      "plan": "สาธารณสุข",
      "type": "งบบุคลากร",
      "total": 663780
    },
    {
      "task": "บริหารทั่วไปเกี่ยวกับสาธารณสุข",
      "area": "ด้านบริการชุมชนและสังคม",
      "plan": "สาธารณสุข",
      "type": "งบดำเนินงาน",
      "total": 3153000
    },
    {
      "task": "บริหารทั่วไปเกี่ยวกับสาธารณสุข",
      "area": "ด้านบริการชุมชนและสังคม",
      "plan": "สาธารณสุข",
      "type": "งบลงทุน",
      "total": 1426000
    },
    {
      "task": "งานโรงพยาบาล",
      "area": "ด้านบริการชุมชนและสังคม",
      "plan": "สาธารณสุข",
      "type": "งบดำเนินงาน",
      "total": 5240000
    },
    {
      "task": "บริการสาธารณสุขและงานสาธารณสุขอื่น",
      "area": "ด้านบริการชุมชนและสังคม",
      "plan": "สาธารณสุข",
      "type": "งบบุคลากร",
      "total": 2555820
    },
    {
      "task": "บริการสาธารณสุขและงานสาธารณสุขอื่น",
      "area": "ด้านบริการชุมชนและสังคม",
      "plan": "สาธารณสุข",
      "type": "งบดำเนินงาน",
      "total": 2367000
    },
    {
      "task": "บริการสาธารณสุขและงานสาธารณสุขอื่น",
      "area": "ด้านบริการชุมชนและสังคม",
      "plan": "สาธารณสุข",
      "type": "งบลงทุน",
      "total": 60000
    },
    {
      "task": "บริการสาธารณสุขและงานสาธารณสุขอื่น",
      "area": "ด้านบริการชุมชนและสังคม",
      "plan": "สาธารณสุข",
      "type": "งบเงินอุดหนุน",
      "total": 400000
    },
    {
      "task": "บริหารทั่วไปเกี่ยวกับสังคมสงเคราะห์",
      "area": "ด้านบริการชุมชนและสังคม",
      "plan": "สังคมสงเคราะห์",
      "type": "งบบุคลากร",
      "total": 3703320
    },
    {
      "task": "บริหารทั่วไปเกี่ยวกับสังคมสงเคราะห์",
      "area": "ด้านบริการชุมชนและสังคม",
      "plan": "สังคมสงเคราะห์",
      "type": "งบดำเนินงาน",
      "total": 7189680
    },
    {
      "task": "บริหารทั่วไปเกี่ยวกับสังคมสงเคราะห์",
      "area": "ด้านบริการชุมชนและสังคม",
      "plan": "สังคมสงเคราะห์",
      "type": "งบลงทุน",
      "total": 1439500
    },
    {
      "task": "สวัสดิการสังคมและสังคมสงเคราะห์",
      "area": "ด้านบริการชุมชนและสังคม",
      "plan": "สังคมสงเคราะห์",
      "type": "งบบุคลากร",
      "total": 7451160
    },
    {
      "task": "สวัสดิการสังคมและสังคมสงเคราะห์",
      "area": "ด้านบริการชุมชนและสังคม",
      "plan": "สังคมสงเคราะห์",
      "type": "งบดำเนินงาน",
      "total": 5080000
    },
    {
      "task": "กำจัดขยะมูลฝอยและสิ่งปฏิกูล",
      "area": "ด้านบริการชุมชนและสังคม",
      "plan": "เคหะและชุมชน",
      "type": "งบดำเนินงาน",
      "total": 700000
    },
    {
      "task": "ส่งเสริมและสนับสนุนความเข้มแข็งชุมชน",
      "area": "ด้านบริการชุมชนและสังคม",
      "plan": "สร้างความเข้มแข็งของชุมชน",
      "type": "งบดำเนินงาน",
      "total": 2837000
    },
    {
      "task": "บริหารทั่วไปเกี่ยวกับศาสนา วัฒนธรม และนันทนาการ",
      "area": "ด้านบริการชุมชนและสังคม",
      "plan": "การศาสนา วัฒนธรรม และนันทนาการ",
      "type": "งบบุคลากร",
      "total": 2803500
    },
    {
      "task": "กีฬาและนันทนาการ",
      "area": "ด้านบริการชุมชนและสังคม",
      "plan": "การศาสนา วัฒนธรรม และนันทนาการ",
      "type": "งบดำเนินงาน",
      "total": 2583400
    },
    {
      "task": "กีฬาและนันทนาการ",
      "area": "ด้านบริการชุมชนและสังคม",
      "plan": "การศาสนา วัฒนธรรม และนันทนาการ",
      "type": "งบลงทุน",
      "total": 1070000
    },
    {
      "task": "ศาสนาวัฒนธรรมท้องถิ่น",
      "area": "ด้านบริการชุมชนและสังคม",
      "plan": "การศาสนา วัฒนธรรม และนันทนาการ",
      "type": "งบดำเนินงาน",
      "total": 5954800
    },
    {
      "task": "ศาสนาวัฒนธรรมท้องถิ่น",
      "area": "ด้านบริการชุมชนและสังคม",
      "plan": "การศาสนา วัฒนธรรม และนันทนาการ",
      "type": "งบลงทุน",
      "total": 5000
    },
    {
      "task": "วิชาการวางแผนและส่งเสริมการท่องเที่ยว",
      "area": "ด้านบริการชุมชนและสังคม",
      "plan": "การศาสนา วัฒนธรรม และนันทนาการ",
      "type": "งบบุคลากร",
      "total": 1358820
    },
    {
      "task": "วิชาการวางแผนและส่งเสริมการท่องเที่ยว",
      "area": "ด้านบริการชุมชนและสังคม",
      "plan": "การศาสนา วัฒนธรรม และนันทนาการ",
      "type": "งบดำเนินงาน",
      "total": 3695000
    },
    {
      "task": "วิชาการวางแผนและส่งเสริมการท่องเที่ยว",
      "area": "ด้านบริการชุมชนและสังคม",
      "plan": "การศาสนา วัฒนธรรม และนันทนาการ",
      "type": "งบเงินอุดหนุน",
      "total": 300000
    },
    {
      "task": "บริหารทั่วไปเกี่ยวกับอุตสาหกรรมและการโยธา",
      "area": "ด้านการเศรษฐกิจ",
      "plan": "อุตสาหกรรมและการโยธา",
      "type": "งบบุคลากร",
      "total": 2926440
    },
    {
      "task": "บริหารทั่วไปเกี่ยวกับอุตสาหกรรมและการโยธา",
      "area": "ด้านการเศรษฐกิจ",
      "plan": "อุตสาหกรรมและการโยธา",
      "type": "งบดำเนินงาน",
      "total": 5700000
    },
    {
      "task": "บริหารทั่วไปเกี่ยวกับอุตสาหกรรมและการโยธา",
      "area": "ด้านการเศรษฐกิจ",
      "plan": "อุตสาหกรรมและการโยธา",
      "type": "งบลงทุน",
      "total": 386000
    },
    {
      "task": "ก่อสร้าง",
      "area": "ด้านการเศรษฐกิจ",
      "plan": "อุตสาหกรรมและการโยธา",
      "type": "งบบุคลากร",
      "total": 33186280
    },
    {
      "task": "ก่อสร้าง",
      "area": "ด้านการเศรษฐกิจ",
      "plan": "อุตสาหกรรมและการโยธา",
      "type": "งบดำเนินงาน",
      "total": 25800600
    },
    {
      "task": "ก่อสร้าง",
      "area": "ด้านการเศรษฐกิจ",
      "plan": "อุตสาหกรรมและการโยธา",
      "type": "งบลงทุน",
      "total": 170711000
    },
    {
      "task": "ส่งเสริมการเกษตร",
      "area": "ด้านการเศรษฐกิจ",
      "plan": "การเกษตร",
      "type": "งบดำเนินงาน",
      "total": 1500000
    },
    {
      "task": "สิ่งแวดล้อมและทรัพยากรธรรมชาติ",
      "area": "ด้านการเศรษฐกิจ",
      "plan": "การเกษตร",
      "type": "งบบุคลากร",
      "total": 5563440
    },
    {
      "task": "สิ่งแวดล้อมและทรัพยากรธรรมชาติ",
      "area": "ด้านการเศรษฐกิจ",
      "plan": "การเกษตร",
      "type": "งบดำเนินงาน",
      "total": 4703600
    },
    {
      "task": "สิ่งแวดล้อมและทรัพยากรธรรมชาติ",
      "area": "ด้านการเศรษฐกิจ",
      "plan": "การเกษตร",
      "type": "งบลงทุน",
      "total": 35000
    },
    {
      "task": "กิจการสถานีขนส่ง/กิจการท่าเรือ",
      "area": "ด้านการเศรษฐกิจ",
      "plan": "การพาณิชย์",
      "type": "งบดำเนินงาน",
      "total": 2964400
    },
    {
      "task": "งบกลาง",
      "area": "ด้านการดำเนินงานอื่น ๆ ",
      "plan": "งบกลาง",
      "type": "งบกลาง",
      "total": 23925400
    }
  ],
  "pao": {
    "name": "ตรัง",
    "incomes": [
      {
        "type": "รายได้จัดเก็บเอง",
        "total": 47367000,
        "categories": [
          {
            "category": "หมวดภาษีอากร",
            "total": 15080000
          },
          {
            "category": "หมวดค่าธรรมเนียม \nค่าปรับและใบอนุญาต",
            "total": 3490000
          },
          {
            "category": "หมวดรายได้จากทรัพย์สิน",
            "total": 15418000
          },
          {
            "category": "หมวดรายได้จากสาธารณูปโภคและกิจการพาณิชย์",
            "total": 1992000
          },
          {
            "category": "หมวดรายได้เบ็ดเตล็ด",
            "total": 11287000
          },
          {
            "category": "หมวดรายได้จากทุน",
            "total": 100000
          }
        ]
      },
      {
        "type": "รายได้จากภาษีที่รัฐบาลจัดเก็บแล้วจัดสรรให้",
        "total": 339880000,
        "categories": [
          {
            "category": "หมวดภาษีจัดสรร",
            "total": 339880000
          }
        ]
      },
      {
        "type": "รายได้ที่รัฐบาลอุดหนุนให้",
        "total": 69353500,
        "categories": [
          {
            "category": "หมวดเงินอุดหนุนทั่วไป",
            "total": 69353500
          }
        ]
      }
    ],
    "population": 0,
    "chiefExecutives": [
      {
        "name": "นาย บุ่นเล้ง โล่สถาพรพิพิธ",
        "inOffice": "20/12/2563 - 19/12/2567",
        "photoUrl": "https://ele.dla.go.th/download/ELE/Candidate/20210312/89CA3842-2002-7FDD-CA1E-4DEC1B847757_UPLOADFILE_DlaELE63.jpg",
        "ownAccount": {
          "asset": 0,
          "debt": 0,
          "income": 0,
          "expense": 0,
          "taxed": 0
        },
        "fillingUrl": "https://drive.google.com/drive/folders/1vqpoOKZkxS-MZ-1x6hLV4TxaDHipzmpv?usp=sharing"
      }
    ],
    "budgetingDocUrl": "",
    "actAiUrl": "https://tinyurl.com/yd62sevw"
  }
}