{
  "total": 630000000,
  "groupedByArea": [
    {
      "area": "ด้านบริหารทั่วไป",
      "total": 141001700,
      "plans": [
        {
          "plan": "บริหารงานทั่วไป",
          "total": 140931700
        },
        {
          "plan": "การรักษาความสงบภายใน",
          "total": 70000
        }
      ]
    },
    {
      "area": "ด้านบริการชุมชนและสังคม",
      "total": 89755600,
      "plans": [
        {
          "plan": "การศึกษา",
          "total": 25950200
        },
        {
          "plan": "สาธารณสุข",
          "total": 36109800
        },
        {
          "plan": "สังคมสงเคราะห์",
          "total": 2000000
        },
        {
          "plan": "เคหะและชุมชน",
          "total": 200000
        },
        {
          "plan": "สร้างความเข้มแข็งของชุมชน",
          "total": 11600000
        },
        {
          "plan": "การศาสนา วัฒนธรรม และนันทนาการ",
          "total": 13895600
        }
      ]
    },
    {
      "area": "ด้านการเศรษฐกิจ",
      "total": 347442600,
      "plans": [
        {
          "plan": "อุตสาหกรรมและการโยธา",
          "total": 336192600
        },
        {
          "plan": "การเกษตร",
          "total": 11250000
        }
      ]
    },
    {
      "area": "ด้านการดำเนินงานอื่น ๆ ",
      "total": 51800100,
      "plans": [
        {
          "plan": "งบกลาง",
          "total": 51800100
        }
      ]
    }
  ],
  "groupedByType": [
    {
      "type": "งบบุคลากร",
      "total": 140412800
    },
    {
      "type": "งบดำเนินงาน",
      "total": 110087300
    },
    {
      "type": "งบลงทุน",
      "total": 310099800
    },
    {
      "type": "งบเงินอุดหนุน",
      "total": 17450000
    },
    {
      "type": "งบรายจ่ายอื่น",
      "total": 150000
    },
    {
      "type": "งบกลาง",
      "total": 51800100
    }
  ],
  "tasks": [
    {
      "task": "บริหารทั่วไป",
      "area": "ด้านบริหารทั่วไป",
      "plan": "บริหารงานทั่วไป",
      "type": "งบบุคลากร",
      "total": 54860900
    },
    {
      "task": "บริหารทั่วไป",
      "area": "ด้านบริหารทั่วไป",
      "plan": "บริหารงานทั่วไป",
      "type": "งบดำเนินงาน",
      "total": 37497200
    },
    {
      "task": "บริหารทั่วไป",
      "area": "ด้านบริหารทั่วไป",
      "plan": "บริหารงานทั่วไป",
      "type": "งบลงทุน",
      "total": 1027800
    },
    {
      "task": "บริหารทั่วไป",
      "area": "ด้านบริหารทั่วไป",
      "plan": "บริหารงานทั่วไป",
      "type": "งบเงินอุดหนุน",
      "total": 200000
    },
    {
      "task": "บริหารทั่วไป",
      "area": "ด้านบริหารทั่วไป",
      "plan": "บริหารงานทั่วไป",
      "type": "งบรายจ่ายอื่น",
      "total": 150000
    },
    {
      "task": "วางแผนสถิติและวิชาการ",
      "area": "ด้านบริหารทั่วไป",
      "plan": "บริหารงานทั่วไป",
      "type": "งบบุคลากร",
      "total": 9907500
    },
    {
      "task": "วางแผนสถิติและวิชาการ",
      "area": "ด้านบริหารทั่วไป",
      "plan": "บริหารงานทั่วไป",
      "type": "งบดำเนินงาน",
      "total": 2905000
    },
    {
      "task": "บริหารงานคลัง",
      "area": "ด้านบริหารทั่วไป",
      "plan": "บริหารงานทั่วไป",
      "type": "งบบุคลากร",
      "total": 16594800
    },
    {
      "task": "บริหารงานคลัง",
      "area": "ด้านบริหารทั่วไป",
      "plan": "บริหารงานทั่วไป",
      "type": "งบดำเนินงาน",
      "total": 17130000
    },
    {
      "task": "บริหารงานคลัง",
      "area": "ด้านบริหารทั่วไป",
      "plan": "บริหารงานทั่วไป",
      "type": "งบลงทุน",
      "total": 658500
    },
    {
      "task": "บริหารทั่วไปเกี่ยวกับการรักษาความสงบภายใน",
      "area": "ด้านบริหารทั่วไป",
      "plan": "การรักษาความสงบภายใน",
      "type": "งบดำเนินงาน",
      "total": 70000
    },
    {
      "task": "บริหารทั่วไปเกี่ยวกับการศึกษา",
      "area": "ด้านบริการชุมชนและสังคม",
      "plan": "การศึกษา",
      "type": "งบบุคลากร",
      "total": 21558700
    },
    {
      "task": "บริหารทั่วไปเกี่ยวกับการศึกษา",
      "area": "ด้านบริการชุมชนและสังคม",
      "plan": "การศึกษา",
      "type": "งบดำเนินงาน",
      "total": 3195500
    },
    {
      "task": "บริหารทั่วไปเกี่ยวกับการศึกษา",
      "area": "ด้านบริการชุมชนและสังคม",
      "plan": "การศึกษา",
      "type": "งบลงทุน",
      "total": 116000
    },
    {
      "task": "บริหารทั่วไปเกี่ยวกับการศึกษา",
      "area": "ด้านบริการชุมชนและสังคม",
      "plan": "การศึกษา",
      "type": "งบเงินอุดหนุน",
      "total": 1080000
    },
    {
      "task": "บริหารทั่วไปเกี่ยวกับสาธารณสุข",
      "area": "ด้านบริการชุมชนและสังคม",
      "plan": "สาธารณสุข",
      "type": "งบบุคลากร",
      "total": 8284200
    },
    {
      "task": "บริหารทั่วไปเกี่ยวกับสาธารณสุข",
      "area": "ด้านบริการชุมชนและสังคม",
      "plan": "สาธารณสุข",
      "type": "งบดำเนินงาน",
      "total": 639600
    },
    {
      "task": "บริหารทั่วไปเกี่ยวกับสาธารณสุข",
      "area": "ด้านบริการชุมชนและสังคม",
      "plan": "สาธารณสุข",
      "type": "งบลงทุน",
      "total": 986000
    },
    {
      "task": "บริการสาธารณสุขและงานสาธารณสุขอื่น",
      "area": "ด้านบริการชุมชนและสังคม",
      "plan": "สาธารณสุข",
      "type": "งบดำเนินงาน",
      "total": 26200000
    },
    {
      "task": "สวัสดิการสังคมและสังคมสงเคราะห์",
      "area": "ด้านบริการชุมชนและสังคม",
      "plan": "สังคมสงเคราะห์",
      "type": "งบดำเนินงาน",
      "total": 2000000
    },
    {
      "task": "กำจัดขยะมูลฝอยและสิ่งปฏิกูล",
      "area": "ด้านบริการชุมชนและสังคม",
      "plan": "เคหะและชุมชน",
      "type": "งบดำเนินงาน",
      "total": 200000
    },
    {
      "task": "ส่งเสริมและสนับสนุนความเข้มแข็งชุมชน",
      "area": "ด้านบริการชุมชนและสังคม",
      "plan": "สร้างความเข้มแข็งของชุมชน",
      "type": "งบดำเนินงาน",
      "total": 1100000
    },
    {
      "task": "ส่งเสริมและสนับสนุนความเข้มแข็งชุมชน",
      "area": "ด้านบริการชุมชนและสังคม",
      "plan": "สร้างความเข้มแข็งของชุมชน",
      "type": "งบเงินอุดหนุน",
      "total": 10500000
    },
    {
      "task": "กีฬาและนันทนาการ",
      "area": "ด้านบริการชุมชนและสังคม",
      "plan": "การศาสนา วัฒนธรรม และนันทนาการ",
      "type": "งบบุคลากร",
      "total": 748500
    },
    {
      "task": "กีฬาและนันทนาการ",
      "area": "ด้านบริการชุมชนและสังคม",
      "plan": "การศาสนา วัฒนธรรม และนันทนาการ",
      "type": "งบดำเนินงาน",
      "total": 5617000
    },
    {
      "task": "กีฬาและนันทนาการ",
      "area": "ด้านบริการชุมชนและสังคม",
      "plan": "การศาสนา วัฒนธรรม และนันทนาการ",
      "type": "งบลงทุน",
      "total": 60100
    },
    {
      "task": "กีฬาและนันทนาการ",
      "area": "ด้านบริการชุมชนและสังคม",
      "plan": "การศาสนา วัฒนธรรม และนันทนาการ",
      "type": "งบเงินอุดหนุน",
      "total": 300000
    },
    {
      "task": "ศาสนาวัฒนธรรมท้องถิ่น",
      "area": "ด้านบริการชุมชนและสังคม",
      "plan": "การศาสนา วัฒนธรรม และนันทนาการ",
      "type": "งบดำเนินงาน",
      "total": 1800000
    },
    {
      "task": "ศาสนาวัฒนธรรมท้องถิ่น",
      "area": "ด้านบริการชุมชนและสังคม",
      "plan": "การศาสนา วัฒนธรรม และนันทนาการ",
      "type": "งบเงินอุดหนุน",
      "total": 5370000
    },
    {
      "task": "บริหารทั่วไปเกี่ยวกับอุตสาหกรรมและการโยธา",
      "area": "ด้านการเศรษฐกิจ",
      "plan": "อุตสาหกรรมและการโยธา",
      "type": "งบบุคลากร",
      "total": 28458200
    },
    {
      "task": "บริหารทั่วไปเกี่ยวกับอุตสาหกรรมและการโยธา",
      "area": "ด้านการเศรษฐกิจ",
      "plan": "อุตสาหกรรมและการโยธา",
      "type": "งบดำเนินงาน",
      "total": 11583000
    },
    {
      "task": "บริหารทั่วไปเกี่ยวกับอุตสาหกรรมและการโยธา",
      "area": "ด้านการเศรษฐกิจ",
      "plan": "อุตสาหกรรมและการโยธา",
      "type": "งบลงทุน",
      "total": 38931400
    },
    {
      "task": "ก่อสร้าง",
      "area": "ด้านการเศรษฐกิจ",
      "plan": "อุตสาหกรรมและการโยธา",
      "type": "งบลงทุน",
      "total": 257220000
    },
    {
      "task": "สิ่งแวดล้อมและทรัพยากรธรรมชาติ",
      "area": "ด้านการเศรษฐกิจ",
      "plan": "การเกษตร",
      "type": "งบดำเนินงาน",
      "total": 150000
    },
    {
      "task": "สิ่งแวดล้อมและทรัพยากรธรรมชาติ",
      "area": "ด้านการเศรษฐกิจ",
      "plan": "การเกษตร",
      "type": "งบลงทุน",
      "total": 11100000
    },
    {
      "task": "งบกลาง",
      "area": "ด้านการดำเนินงานอื่น ๆ ",
      "plan": "งบกลาง",
      "type": "งบกลาง",
      "total": 51800100
    }
  ],
  "pao": {
    "name": "บุรีรัมย์",
    "incomes": [
      {
        "type": "รายได้จัดเก็บเอง",
        "total": 50752000,
        "categories": [
          {
            "category": "หมวดภาษีอากร",
            "total": 37000000
          },
          {
            "category": "หมวดค่าธรรมเนียม \nค่าปรับและใบอนุญาต",
            "total": 990000
          },
          {
            "category": "หมวดรายได้จากทรัพย์สิน",
            "total": 7726000
          },
          {
            "category": "หมวดรายได้เบ็ดเตล็ด",
            "total": 5031000
          },
          {
            "category": "หมวดรายได้จากทุน",
            "total": 5000
          }
        ]
      },
      {
        "type": "รายได้จากภาษีที่รัฐบาลจัดเก็บแล้วจัดสรรให้",
        "total": 480148200,
        "categories": [
          {
            "category": "หมวดภาษีจัดสรร",
            "total": 480148200
          }
        ]
      },
      {
        "type": "รายได้ที่รัฐบาลอุดหนุนให้",
        "total": 99099800,
        "categories": [
          {
            "category": "หมวดเงินอุดหนุนทั่วไป",
            "total": 99099800
          }
        ]
      }
    ],
    "population": 0,
    "chiefExecutives": [
      {
        "name": "นาย ภูษิต เล็กอุดากร",
        "inOffice": "20/12/2563 - 19/12/2567",
        "photoUrl": "https://ele.dla.go.th/download/ELE/Candidate/20220408/BD2216B4-623B-58BC-49FA-7ABC609D5192_UPLOADFILE_DlaELE63.jpeg",
        "ownAccount": {
          "asset": 3071002,
          "debt": 8000000,
          "income": 906360,
          "expense": 1085600,
          "taxed": 190638
        },
        "spouseAccount": {
          "asset": 29426463,
          "debt": 4866837.1,
          "income": 180000,
          "expense": 84000,
          "taxed": 234000
        },
        "childrenAccount": {
          "asset": 0,
          "debt": 0,
          "income": 0,
          "expense": 0
        },
        "fillingUrl": "https://drive.google.com/drive/folders/1RTRXFOIGEH8Ff4TNorASSfJmfnIzXqd6?usp=sharing"
      }
    ],
    "budgetingDocUrl": "https://drive.google.com/file/d/1HyXg0Fla0BArfupbC_b0vxbf0y5bPxaY/view?usp=sharing",
    "actAiUrl": "https://tinyurl.com/yauq3zsb"
  }
}